ginkgo_tools/__init__.py
ginkgo_tools/tools_log.py
ginkgo_tools/tools_threading_target.py
ginkgo_tools/tools_time.py
ginkgo_tools-0.1.7.dist-info/METADATA
ginkgo_tools-0.1.7.dist-info/WHEEL
ginkgo_tools-0.1.7.dist-info/top_level.txt
ginkgo_tools-0.1.7.dist-info/RECORD
