Metadata-Version: 2.4
Name: ginkgo-tools
Version: 0.1.7
Summary: 一套实用的 Python 工具库，包含日志、时间处理和多线程相关的工具函数
Author-email: GINKGO <495466557@qq.com>
Keywords: tools,utilities,logging,time,threading
Classifier: Development Status :: 3 - Alpha
Classifier: Intended Audience :: Developers
Classifier: License :: OSI Approved :: MIT License
Classifier: Programming Language :: Python :: 3
Classifier: Programming Language :: Python :: 3.6
Classifier: Programming Language :: Python :: 3.7
Classifier: Programming Language :: Python :: 3.8
Classifier: Programming Language :: Python :: 3.9
Classifier: Programming Language :: Python :: 3.10
Classifier: Programming Language :: Python :: 3.11
Requires-Python: >=3.6
